hiveflow/__init__.py
hiveflow/cli.py
hiveflow/version.py
hiveflow/core/__init__.py
hiveflow/core/coordinator.py
hiveflow/core/task.py
hiveflow/core/worker.py
hiveflow/templates/Dockerfile.coordinator.template
hiveflow/templates/Dockerfile.monitor.template
hiveflow/templates/Dockerfile.worker.template
hiveflow/templates/README.md.template
hiveflow/templates/custom_task.py.template
hiveflow/templates/custom_worker.py.template
hiveflow/templates/docker-compose.dev.yml.template
hiveflow/templates/docker-compose.yml.template
hiveflow/templates/pyproject.toml.template
hiveflow/templates/setup.py.template
hiveflow/templates/task.py.template
hiveflow/templates/worker.py.template
hiveflow-1.0.1.dist-info/LICENSE
hiveflow-1.0.1.dist-info/METADATA
hiveflow-1.0.1.dist-info/WHEEL
hiveflow-1.0.1.dist-info/entry_points.txt
hiveflow-1.0.1.dist-info/top_level.txt
hiveflow-1.0.1.dist-info/RECORD
