Metadata-Version: 2.2
Name: HiveFlow
Version: 1.0.1
Summary: A scalable, distributed producer/consumer framework for Python
Home-page: https://github.com/changyy/py-HiveFlow
Author: changyy
Author-email: changyy.csie@gmail.com
Project-URL: Bug Tracker, https://github.com/changyy/py-HiveFlow/issues
Project-URL: Documentation, https://py-hiveflow.readthedocs.io
Project-URL: Source Code, https://github.com/changyy/py-HiveFlow
Classifier: Development Status :: 3 - Alpha
Classifier: Intended Audience :: Developers
Classifier: License :: OSI Approved :: MIT License
Classifier: Programming Language :: Python :: 3
Classifier: Programming Language :: Python :: 3.12
Classifier: Operating System :: OS Independent
Classifier: Topic :: Software Development :: Libraries :: Application Frameworks
Classifier: Topic :: Software Development :: Libraries :: Python Modules
Requires-Python: >=3.12
License-File: LICENSE
Requires-Dist: fastapi>=0.104.0
Requires-Dist: uvicorn>=0.23.2
Requires-Dist: redis>=5.0.0
Requires-Dist: asyncpg>=0.28.0
Requires-Dist: sqlalchemy>=2.0.22
Requires-Dist: pydantic>=2.4.2
Requires-Dist: aiohttp>=3.8.6
Requires-Dist: click>=8.1.7
Requires-Dist: jinja2>=3.1.2
Provides-Extra: dev
Requires-Dist: pytest>=7.4.2; extra == "dev"
Requires-Dist: pytest-asyncio>=0.21.1; extra == "dev"
Requires-Dist: pytest-cov>=4.1.0; extra == "dev"
Requires-Dist: black>=23.10.0; extra == "dev"
Requires-Dist: isort>=5.12.0; extra == "dev"
Requires-Dist: mypy>=1.6.1; extra == "dev"
Requires-Dist: flake8>=6.1.0; extra == "dev"
Requires-Dist: pre-commit>=3.5.0; extra == "dev"
Requires-Dist: sphinx>=7.2.6; extra == "dev"
Requires-Dist: sphinx-rtd-theme>=1.3.0; extra == "dev"
Dynamic: author
Dynamic: author-email
Dynamic: classifier
Dynamic: description
Dynamic: description-content-type
Dynamic: home-page
Dynamic: project-url
Dynamic: provides-extra
Dynamic: requires-dist
Dynamic: requires-python
Dynamic: summary
